Metadata-Version: 1.1
Name: joseph-web-hello-world
Version: 0.1.5
Summary: A basic HTTP handler for Joseph.
Home-page: https://github.com/NiekKeijzer/HTTPTest
Author: Niek Keijzer
Author-email: info@niekkeijzer.com
License: UNKNOWN
Download-URL: https://github.com/NiekKeijzer/HTTPTest/archive/0.1.5.tar.gaz
Keywords: http,web,hello_worldjoseph
Platform: UNKNOWN
